Metadata-Version: 1.0
Name: boringstonks
Version: 0.0.8
Summary: API client for boring stonks
Home-page: UNKNOWN
Author: Kevin Per
Author-email: kevin.per@protonmail.com
License: UNKNOWN
Keywords: python
Platform: UNKNOWN
